library_entity/__init__.py
library_entity/base.py
library_entity/city.py
library_entity/country.py
library_entity/department.py
library_entity/player.py
library_entity/team.py
library_entity/teamplayer.py
library_entity/user.py
goallteam_library_entity-1.0.12.dist-info/METADATA
goallteam_library_entity-1.0.12.dist-info/WHEEL
goallteam_library_entity-1.0.12.dist-info/top_level.txt
goallteam_library_entity-1.0.12.dist-info/RECORD
